{
  "categorias": [
    {
      "titulo": "Pr Augustus Nicodemus",
      "link": "https://www.youtube.com/watch?v=LuWQkaizYPw",
      "cor": "#6BD1FF",
      "link_extra": {
        "text": "Pregações",
        "url": "https://www.youtube.com/watch?v=LuWQkaizYPw"
      },
      "videos": [
        {
          "titulo": "Eleição e Predestinação - Augustus Nicodemus",
          "url": "https://www.youtube.com/watch?v=LuWQkaizYPw"
        },
        {
          "titulo": "Eleição e Predestinação - Augustus Nicodemus",
          "url": "https://www.youtube.com/watch?v=LuWQkaizYPw"
        },
        {
          "titulo": "OPS Livre Arbítrio - Augustus Nicodemus",
          "url": "https://www.youtube.com/watch?v=LFC2qpnNB6w"
        },
        {
          "titulo": "Onisciência, Onipotência e Onipresença de Deus - Augustus Nicodemus",
          "url": "https://www.youtube.com/watch?v=KmNW1B254V0"
        },
        {
          "titulo": "O que Jesus exige de seus Seguidores - Augustus Nicodemus",
          "url": "https://www.youtube.com/watch?v=4mZHw2hwZVk"
        },
        {
          "titulo": "Somente a Fé - Augustus Nicodemus",
          "url": "https://www.youtube.com/watch?v=lszHFOFtnmg"
        },
        {
          "titulo": "Como ser um crente fiel - Augustus Nicodemus",
          "url": "https://www.youtube.com/watch?v=yFjz1LjFvMw"
        },
        {
          "titulo": "Amar e servir ao Senhor quando tudo está dando errado - Augustus Nicodemus",
          "url": "https://www.youtube.com/watch?v=LxFUiubJTlQ&pbjreload=101"
        }        
      ]
    },
    {
      "titulo": "Pr Hernandes Dias Lopes",
      "cor": "#00C86F",
      "link_extra": {
        "text": "Pregações",
        "url": "https://www.alura.com.br/cursos-online-programacao"
      },
      "videos": [
        {
          "titulo": "Se Deus é por nós, quem será contra nós? Rev. Hernandes Dias Lope",
          "url": "https://www.youtube.com/watch?v=FJl5EsHjh7I"
        },
        {
          "titulo": "Quando a crise vem da própria família | Rev. Hernandes Dias Lopes",
          "url": "https://www.youtube.com/watch?v=W9mx3a_2ySM"
        },
        {
          "titulo": "As sete mensagens da ressurreição | Pr Hernandes Dias Lopes",
          "url": "https://www.youtube.com/watch?v=wRXGrS0bEAU"
        },
        {
          "titulo": "Abrindo o jogo sobre o dízimo | Rev Hernandes Dias Lopes",
          "url": "https://www.youtube.com/watch?v=a6ws5UWqPvU"
        }, 
        {
          "titulo": "Batalha espiritual - Pr Hernandes Dias Lopes",
          "url": "https://www.youtube.com/watch?v=qA_ti9gzQOQ"
        }
      ]
    },
    {
      "titulo": "Pr Paulo Salustiano",
      "cor": "#9cd33b",
      "link_extra": {
        "text": "Série devocional",
        "url": "https://www.youtube.com/c/PIBIpaporanga/videos"
      },
      "videos": [
        {
          "titulo": "Alegria",
          "url": "https://www.youtube.com/watch?v=Nqc4btYi_4w"
        },
        {
          "titulo": "Distrações",
          "url": "https://www.youtube.com/watch?v=poBphcC0umI"
        },
        {
          "titulo": "Pode confiar!",
          "url": "https://www.youtube.com/watch?v=s68zBO8y5R8"
        },
        {
          "titulo": "Deus sabe o que faz",
          "url": "https://www.youtube.com/watch?v=Y2K8-thCPug"
        }
      ]
    },
    {
      "titulo": "Filmes",
      "cor": "orange",
      "videos": [
        {
          "titulo": "Deus Não Está Morto 2",
          "url": "https://www.youtube.com/watch?v=9ZoMluNRODw"
        },
        {
          "titulo": "Deus Não Está Morto - Uma Luz na Escuridão",
          "url": "https://www.youtube.com/watch?v=LXnS4OaZD30"
        },
        {
          "titulo": "Quarto de Guerra",
          "url": "https://www.youtube.com/watch?v=1klpQcOJxLM"
        },
        {
          "titulo": "Até o Último Homem ",
          "url": "https://www.youtube.com/watch?v=4s4UCxCv_OE"
        }
      ]
    },
    {
      "titulo": "Games",
      "cor": "red",
      "link_extra": {
        "text": "Formação de Jogos na Alura",
        "url": "https://www.alura.com.br/formacao-jogos-unity"
      },
      "videos": [
        {
          "titulo": "Final Fantasy 7",
          "url": "https://www.youtube.com/watch?v=I_ATSCTnUD8"
        },
        {
          "titulo": "Assassins Creed Valhalla",
          "url": "https://www.youtube.com/watch?v=KDfdjB9uL0U"
        },
        {
          "titulo": "God of War 4",
          "url": "https://www.youtube.com/watch?v=FyIwEFXOcaE"
        },
        {
          "titulo": "Resident Evil 8",
          "url": "https://www.youtube.com/watch?v=JSapXD9vxYA"
        },
        {
          "titulo": "Pokémon Let's Go Pikachu/Eevee",
          "url": "https://www.youtube.com/watch?v=L56q_k2ydrs"
        }
      ]
    },
    {
      "titulo": "Dois Dedos de Teologia",
      "cor": "#6b5be2",
      "link_extra": {
        "text": "Vídeos",
        "url": "https://alura.com.br/curso-online-aprender-a-aprender-tecnicas-para-seu-autodesenvolvimento"
      },
      "videos": [
        {
          "titulo": "CONTRADIÇÃO? QUANTAS FILHAS DE LÓ?",
          "url": "https://www.youtube.com/watch?v=uQp5W_Ds2Yg"
        },
        {
          "titulo": "A TEOLOGIA DA PROSPERIDADE ESTÁ CERTA? PECADOS PARA A MORTE?",
          "url": "https://www.youtube.com/watch?v=SrtCNhDttPc"
        },
        {
          "titulo": "O PÃO VIRA CORPO DE CRISTO NA CEIA?",
          "url": "https://www.youtube.com/watch?v=vNOrC9lepWs"
        },
        {
          "titulo": "SATANÁS ESTÁ PRESO OU NÃO?",
          "url": "https://www.youtube.com/watch?v=8j4Q-PLjBnA"
        },
        {
          "titulo": "COMEÇO A BÍBLIA POR ONDE? PREGAR DEPRIMIDO? CIÚMES DO PASTOR?",
          "url": "https://www.youtube.com/watch?v=zA-HWB33gcE"
        }
      ]
    }
  ]
}